texttablescoop/__init__.py
texttablescoop/base_parser.py
texttablescoop/cli.py
texttablescoop/parser.py
texttablescoop/utils.py
texttablescoop/archive_parsers/__init__.py
texttablescoop/archive_parsers/zip_parser.py
texttablescoop/table_parsers/__init__.py
texttablescoop/table_parsers/csv_parser.py
texttablescoop/table_parsers/excel_parser.py
texttablescoop/text_parsers/__init__.py
texttablescoop/text_parsers/html_parser.py
texttablescoop/text_parsers/txt_parser.py
texttablescoop-0.1.2.data/scripts/texttablescoop
texttablescoop-0.1.2.dist-info/LICENSE
texttablescoop-0.1.2.dist-info/METADATA
texttablescoop-0.1.2.dist-info/WHEEL
texttablescoop-0.1.2.dist-info/top_level.txt
texttablescoop-0.1.2.dist-info/RECORD
