Metadata-Version: 2.1
Name: texttablescoop
Version: 0.1.2
Summary: Library for obtaining and organizing text data from your Project Folders.
Author-email: Anton Potapov <fgreyeducation@gmail.com>
License: MIT License
License-File: LICENSE
Requires-Dist: argparse
Requires-Dist: argcomplete
Requires-Dist: pandas
Requires-Dist: xlsx2pandas
